document_tools/__init__.py
document_tools/documents/__init__.py
document_tools/documents/base.py
document_tools/encoders/__init__.py
document_tools/encoders/encoders.py
document_tools/tokenize.py
document_tools/utils.py
document_tools-0.1.2.dist-info/LICENSE
document_tools-0.1.2.dist-info/WHEEL
document_tools-0.1.2.dist-info/METADATA
document_tools-0.1.2.dist-info/RECORD
